i18n_modern/__init__.py
i18n_modern/_accel.py
i18n_modern/_cy_helpers.c
i18n_modern/_cy_helpers.pyx
i18n_modern/ast_evaluator.py
i18n_modern/conditional_evaluator.py
i18n_modern/helpers.py
i18n_modern/i18n.py
i18n_modern/types.py
i18n_modern/value_substitution.py
i18n_modern-0.2.1.dist-info/METADATA
i18n_modern-0.2.1.dist-info/WHEEL
i18n_modern-0.2.1.dist-info/licenses/LICENSE
i18n_modern-0.2.1.dist-info/RECORD
