Metadata-Version: 2.4
Name: i18n_modern
Version: 0.2.1
Summary: A modern internationalization library for Python with support for JSON, YAML, and TOML
Project-URL: Homepage, https://github.com/UrielCuriel/python_i18n_modern
Project-URL: Repository, https://github.com/UrielCuriel/python_i18n_modern
Project-URL: Issues, https://github.com/UrielCuriel/python_i18n_modern/issues
Author-email: Uriel Curiel <urielcurrel@outlook.com>
License: MIT
License-File: LICENSE
Keywords: i18n,internationalization,l10n,localization,translation
Classifier: Development Status :: 4 - Beta
Classifier: Intended Audience :: Developers
Classifier: License :: OSI Approved :: MIT License
Classifier: Programming Language :: Python :: 3
Classifier: Programming Language :: Python :: 3.8
Classifier: Programming Language :: Python :: 3.9
Classifier: Programming Language :: Python :: 3.10
Classifier: Programming Language :: Python :: 3.11
Classifier: Programming Language :: Python :: 3.12
Requires-Python: >=3.8
Provides-Extra: all
Requires-Dist: pyyaml>=6.0; extra == 'all'
Requires-Dist: tomli>=2.3.0; (python_version < '3.11') and extra == 'all'
Provides-Extra: benchmark
Requires-Dist: cython>=3.0.0; extra == 'benchmark'
Requires-Dist: i18nice; extra == 'benchmark'
Requires-Dist: pyi18n-v2>=1.2.0; extra == 'benchmark'
Requires-Dist: python-i18n>=0.3.9; extra == 'benchmark'
Requires-Dist: toml-i18n; extra == 'benchmark'
Provides-Extra: dev
Requires-Dist: basedpyright; extra == 'dev'
Requires-Dist: cython>=3.0.0; extra == 'dev'
Requires-Dist: pyrefly; extra == 'dev'
Requires-Dist: pytest; extra == 'dev'
Requires-Dist: pytest-cov; extra == 'dev'
Requires-Dist: ruff; extra == 'dev'
Provides-Extra: toml
Requires-Dist: tomli>=2.3.0; (python_version < '3.11') and extra == 'toml'
Provides-Extra: yaml
Requires-Dist: pyyaml>=6.0; extra == 'yaml'
